how.py
howdo-0.1.1.dist-info/METADATA
howdo-0.1.1.dist-info/WHEEL
howdo-0.1.1.dist-info/entry_points.txt
howdo-0.1.1.dist-info/top_level.txt
howdo-0.1.1.dist-info/RECORD
