Metadata-Version: 2.1
Name: howdo
Version: 0.1.1
Summary: A terminal app to query xAI's Grok API
Home-page: https://github.com/thegje/how
Author: thegje
Author-email: thegje@gmail.com
License: UNKNOWN
Platform: UNKNOWN
Classifier: Programming Language :: Python :: 3
Classifier: License :: OSI Approved :: MIT License
Classifier: Operating System :: POSIX :: Linux
Requires-Python: >=3.6
Requires-Dist: requests
